tests/__init__.py
tests/conftest.py
tests/test_core_single_stage.py
tests/test_core_two_stage.py
tests/test_core_two_stage_ert.py
tests/test_demand.py
tests/test_eeweather_wrapper.py
tests/test_equipment_type.py
tests/test_importers_single_stage.py
tests/test_importers_two_stage.py
tests/test_importers_two_stage_ert.py
tests/test_metrics_single_stage.py
tests/test_metrics_two_stage.py
tests/test_metrics_two_stage_ert.py
tests/test_parallel.py
tests/test_stations.py
tests/test_stats.py
tests/fixtures/__init__.py
tests/fixtures/single_stage.py
tests/fixtures/thermostats.py
tests/fixtures/two_stage.py
tests/fixtures/two_stage_ert.py
thermostat_nw/__init__.py
thermostat_nw/climate_zone.py
thermostat_nw/columns.py
thermostat_nw/core.py
thermostat_nw/eeweather_wrapper.py
thermostat_nw/equipment_type.py
thermostat_nw/exporters.py
thermostat_nw/importers.py
thermostat_nw/multiple.py
thermostat_nw/parallel.py
thermostat_nw/stations.py
thermostat_nw/stats.py
thermostat_nw/resources/Building America Climate Zone to Zipcode Database_Rev2_2016.09.08.csv
thermostat_nw/resources/NationalAverageClimateZoneWeightings.csv
thermostat_nw/resources/__init__.py
thermostat_nw/resources/heatpump_baseline_default.csv
thermostat_nw/resources/northwest_climate_zone_mapping.csv
thermostat_nw/resources/regional_baselines.csv
thermostat_nw/resources/zipcode_usaf_station.json
thermostat_nw/resources/temperature_baselines_nw/__init__.py
thermostat_nw/resources/temperature_baselines_nw/temperature_baseline_cz1_central.csv
thermostat_nw/resources/temperature_baselines_nw/temperature_baseline_cz1_default.csv
thermostat_nw/resources/temperature_baselines_nw/temperature_baseline_cz1_heat_pump.csv
thermostat_nw/resources/temperature_baselines_nw/temperature_baseline_cz1_none.csv
thermostat_nw/resources/temperature_baselines_nw/temperature_baseline_cz2_central.csv
thermostat_nw/resources/temperature_baselines_nw/temperature_baseline_cz2_default.csv
thermostat_nw-0.1.3.dist-info/METADATA
thermostat_nw-0.1.3.dist-info/WHEEL
thermostat_nw-0.1.3.dist-info/top_level.txt
thermostat_nw-0.1.3.dist-info/RECORD
