Metadata-Version: 2.1
Name: thermostat-nw
Version: 0.1.3
Summary: Calculate connected thermostat savings
Home-page: https://github.com/hshaban/epathermostat_nw
Author: Empower Dataworks + Apex Analytics. Forked from https://github.com/EPAENERGYSTAR/epathermostat.
Author-email: UNKNOWN
License: MIT
Keywords: thermostat savings EPA
Platform: UNKNOWN
Classifier: Development Status :: 4 - Beta
Classifier: License :: OSI Approved :: MIT License
Classifier: Programming Language :: Python :: 3
Requires-Dist: eemeter (==2.5.2)
Requires-Dist: eeweather (==0.3.24)
Requires-Dist: numpy (==1.19.4)
Requires-Dist: pandas (==0.25.3)
Requires-Dist: sqlalchemy (==1.3.1)
Requires-Dist: zipcodes (==1.1.2)
